regml/RegML.py
regml/RegML_GUI.py
regml/__init__.py
regml-0.0.2.dist-info/LICENSE
regml-0.0.2.dist-info/METADATA
regml-0.0.2.dist-info/WHEEL
regml-0.0.2.dist-info/top_level.txt
regml-0.0.2.dist-info/RECORD
