Metadata-Version: 2.1
Name: regml
Version: 0.0.2
Summary: Regularization Methods for Machine Learning
Home-page: https://nikeshbajaj.github.io/Regularization_for_Machine_Learning/
Author: Nikesh Bajaj
Author-email: nikkeshbajaj@gmail.com
License: MIT
Download-URL: https://github.com/Nikeshbajaj/Regularization_for_Machine_Learning/tarball/0.0.2
Keywords: Regularization methods Machine Learning Regularized Least Squares Nu-Method Iterative Landweber Method Singular Value Decomposition,Kernal Lerning K-Fold
Platform: UNKNOWN
Classifier: Programming Language :: Python :: 3
Classifier: Programming Language :: Python :: 2.7
Classifier: License :: OSI Approved :: MIT License
Classifier: Operating System :: OS Independent
Requires-Dist: numpy (>=1.10.4)
Requires-Dist: matplotlib (>=0.98)
Requires-Dist: scipy (>=0.12)
